django_setup_tools/__init__.py
django_setup_tools/apps.py
django_setup_tools/management/__init__.py
django_setup_tools/management/commands/__init__.py
django_setup_tools/management/commands/setup.py
django_setup_tools/scripts.py
django_setup_tools-0.2.5.dist-info/LICENSE
django_setup_tools-0.2.5.dist-info/METADATA
django_setup_tools-0.2.5.dist-info/WHEEL
django_setup_tools-0.2.5.dist-info/RECORD
