Metadata-Version: 2.1
Name: django-setup-tools
Version: 0.2.5
Summary: Declaratively setup Django before deployment in any environment
License: MIT
Author: Sam
Author-email: samuel.scott.jennings@gmail.com
Requires-Python: >=3.10,<4.0
Classifier: License :: OSI Approved :: MIT License
Classifier: Programming Language :: Python :: 3
Classifier: Programming Language :: Python :: 3.10
Classifier: Programming Language :: Python :: 3.11
Classifier: Programming Language :: Python :: 3.12
Requires-Dist: django (>=3.2)
